orangelib/__init__.py
orangelib/model.py
orangelib/net.py
orangelib-0.4.0.dist-info/METADATA
orangelib-0.4.0.dist-info/WHEEL
orangelib-0.4.0.dist-info/top_level.txt
orangelib-0.4.0.dist-info/RECORD
